nonebot_plugin_easy_translate/__init__.py
nonebot_plugin_easy_translate/config.py
nonebot_plugin_easy_translate/gtranslate/client.py
nonebot_plugin_easy_translate/gtranslate/constants.py
nonebot_plugin_easy_translate/gtranslate/gtoken.py
nonebot_plugin_easy_translate/gtranslate/models.py
nonebot_plugin_easy_translate/gtranslate/urls.py
nonebot_plugin_easy_translate/gtranslate/utils.py
nonebot_plugin_easy_translate-0.2.4.dist-info/METADATA
nonebot_plugin_easy_translate-0.2.4.dist-info/WHEEL
nonebot_plugin_easy_translate-0.2.4.dist-info/top_level.txt
nonebot_plugin_easy_translate-0.2.4.dist-info/RECORD
