Metadata-Version: 2.4
Name: nonebot-plugin-easy-translate
Version: 0.2.4
Summary: Nonebot2 谷歌翻译插件
Requires-Python: >=3.8
Requires-Dist: httpx[http2]>=0.26.0
Requires-Dist: nonebot-adapter-onebot>=2.0.0
Requires-Dist: nonebot2>=2.0.0
